{
    "url": "https://geizhals.at/asus-tuf-gaming-vg32aqa1a-90lm07l0-b02370-a2878838.html?hloc=at&hloc=de",
    "product_name": "ASUS TUF Gaming VG32AQA1A, 31.5\"",
    "product_details": [
        {
            "name": "Diagonale",
            "value": "31.5\"/\u200b80cm"
        },
        {
            "name": "Aufl\u00f6sung",
            "value": "2560x1440, 16:9, 93ppi"
        },
        {
            "name": "Helligkeit",
            "value": "300cd/\u200bm\u00b2"
        },
        {
            "name": "Kontrast",
            "value": "3.000:1 (statisch), 100.000.000:1 (dynamisch)"
        },
        {
            "name": "Reaktionszeit",
            "value": "keine Angabe (GtG), 1ms (MPRT)"
        },
        {
            "name": "Blickwinkel",
            "value": "178\u00b0/\u200b178\u00b0"
        },
        {
            "name": "Panel",
            "value": "VA"
        },
        {
            "name": "Form",
            "value": "gerade (flat)"
        },
        {
            "name": "Beschichtung",
            "value": "matt (non-glare)"
        },
        {
            "name": "Hintergrundbeleuchtung",
            "value": "White-LED, flicker-free, Blaulichtfilter"
        },
        {
            "name": "HDR",
            "value": "HDR10"
        },
        {
            "name": "Farbtiefe",
            "value": "8bit (16.7 Mio. Farben)"
        },
        {
            "name": "FRC",
            "value": "unbekannt"
        },
        {
            "name": "Farbraum",
            "value": "keine Angabe (sRGB), keine Angabe (Adobe RGB), keine Angabe (DCI-P3), keine Angabe (REC 709), keine Angabe (REC 2020)"
        },
        {
            "name": "Bildwiederholfrequenz",
            "value": "170Hz"
        },
        {
            "name": "Variable Synchronisierung",
            "value": "Adaptive Sync, AMD FreeSync Premium (48-170Hz via DisplayPort, 48-144Hz via HDMI, mit LFC-Support, mit HDR)"
        },
        {
            "name": "Unsch\u00e4rfereduktionsfunktion",
            "value": "ASUS Extreme Low Motion Blur (ELMB, max. 170Hz)"
        },
        {
            "name": "Signalfrequenz",
            "value": "250kHz (horizontal), 48-170Hz (vertikal)"
        },
        {
            "name": "Anschl\u00fcsse",
            "value": "2x HDMI 2.0 (144Hz@2560x1440), 1x DisplayPort 1.2 (170Hz@2560x1440)"
        },
        {
            "name": "Weitere Anschl\u00fcsse",
            "value": "N/\u200bA"
        },
        {
            "name": "USB-Hub Out",
            "value": "N/\u200bA"
        },
        {
            "name": "USB-Hub In",
            "value": "N/\u200bA"
        },
        {
            "name": "Audio",
            "value": "Lautsprecher (2x 2W), 1x Line-Out"
        },
        {
            "name": "Ergonomie",
            "value": "N/\u200bA (h\u00f6henverstellbar), N/\u200bA (Pivot), N/\u200bA (drehbar), +20\u00b0/\u200b-5\u00b0 (neigbar), keine Angabe (Schr\u00e4glage)"
        },
        {
            "name": "Farbe",
            "value": "schwarz (Displayrahmen), schwarz (untere Blende), schwarz (Standfu\u00df), schwarz (R\u00fcckseite)"
        },
        {
            "name": "VESA",
            "value": "100x100 (frei)"
        },
        {
            "name": "Leistungsaufnahme",
            "value": "keine Angabe (maximal), 26W (typisch), keine Angabe (Energielabel alt A+++ bis G), 0.5W (Standby)"
        },
        {
            "name": "Energieeffizienzklasse SDR (A bis G)",
            "value": "E"
        },
        {
            "name": "Energieverbrauch SDR",
            "value": "27kWh/\u200b1000h"
        },
        {
            "name": "Energieeffizienzklasse HDR (A bis G)",
            "value": "G"
        },
        {
            "name": "Energieverbrauch HDR",
            "value": "33kWh/\u200b1000h"
        },
        {
            "name": "Stromversorgung",
            "value": "DC-In (externes Netzteil)"
        },
        {
            "name": "Anwendung",
            "value": "station\u00e4r"
        },
        {
            "name": "Screen-to-Body-Ratio",
            "value": "89.6% (berechnet)"
        },
        {
            "name": "Abmessungen (BxHxT)",
            "value": "716.3x496.2x213.81mm (mit Standfu\u00df), 716.3x426.2x54.87mm (ohne Standfu\u00df)"
        },
        {
            "name": "Gewicht",
            "value": "6.70kg (mit Standfu\u00df), 5.70kg (ohne Standfu\u00df)"
        },
        {
            "name": "Besonderheiten",
            "value": "Slim Bezel, mechanische Tasten mit Steuerkreuz, Sicherheitsschloss (Kensington), HDCP 2.2"
        },
        {
            "name": "Herstellergarantie",
            "value": "drei Jahre"
        },
        {
            "name": "USB-Schreibweise",
            "value": "Link"
        },
        {
            "name": "Letztes Preisupdate",
            "value": "02.10.2023, 09:44"
        },
        {
            "name": "Gelistet seit",
            "value": "17.01.2023, 10:53"
        }
    ],
    "offers": [
        {
            "shop_name": "CSV-Direct.de",
            "price": 294.61,
            "offer_link": "https://www.csv-direct.de/artinfo.php?artnr=AGX1621933&KATEGORIE=162&pva=geizhals2",
            "promotion_description": null
        },
        {
            "shop_name": "cw-mobile.de",
            "price": 295.99,
            "offer_link": "https://click.cptrack.de/?rd=true&k=5QNCBYB9xMh6DJycvhgeWxNAUQqhivLsH5YLTiZwgT62UOq56iJhcGuf7B8oqsLuiqCdpe0PJ81gw-kNg21utg~~&rdlink=https%3A%2F%2Fwww.cw-mobile.de%2Fasus-tuf-gaming-vg32aqa1a-81-3-cm-32-zoll-gaming-monitor.html%3Futm_source%3DPSM%26utm_medium%3DGeizhals%26utm_campaign%3DPSM",
            "promotion_description": null
        },
        {
            "shop_name": "playox (AT)",
            "price": 298.17,
            "offer_link": "https://www.playox.de/productredirect/index/sku/25966862?sPartner=p-geizhals-at&campaign=psm/geizhals-at/",
            "promotion_description": null
        },
        {
            "shop_name": "office-partner (AT)",
            "price": 298.18,
            "offer_link": "https://www.office-partner.de/productredirect/index/sku/25966862?sPartner=p-geizhals-at&campaign=psm/geizhals-at/",
            "promotion_description": null
        },
        {
            "shop_name": "alza.at",
            "price": 299.9,
            "offer_link": "https://www.alza.at/31-5-asus-tuf-gaming-vg32aqa1a-d7594250.htm?kampan=geizhals_at_monitory_herni_ostatni-frekvence_wa049m1d0c&utm_source=geizhals_at&utm_medium=product&utm_campaign=geizhals_at_monitory_herni_ostatni-frekvence_wa049m1d0c",
            "promotion_description": null
        },
        {
            "shop_name": "Media Markt.at",
            "price": 299.99,
            "offer_link": "https://www.mediamarkt.at/de/product/_asus-gaming-monitor-tuf-vg32aqa1a-315-zoll-wqhd-1ms-mprt-300cd-170hz-freesync-premium-va-panel-4w-audio-schwarz-1927364.html?utm_source=geizhals&utm_medium=psm-product%20feed&utm_term=1927364&utm_campaign=price%20comparison_mm-ka-produkte%20onl-nat_3222",
            "promotion_description": null
        },
        {
            "shop_name": "haym.infotec",
            "price": 300.01,
            "offer_link": "https://haym.info/produktdetails?id=3C01071",
            "promotion_description": null
        },
        {
            "shop_name": "mylemon.at",
            "price": 300.93,
            "offer_link": "https://www.mylemon.at/artikel/asus/90lm07l0_b02370/80-1cm-gaming-vg32aqa1a-wqhd.html",
            "promotion_description": null
        },
        {
            "shop_name": "Proshop.at",
            "price": 300.94,
            "offer_link": "https://www.proshop.at/Bildschirm/ASUS-32-Bildschirm-VG32AQA1A-Black-1-ms-AMD-FreeSync-Premium/3135509?utm_source=geizhals&utm_medium=cpc&utm_campaign=pricesite",
            "promotion_description": null
        },
        {
            "shop_name": "Jacob Elektronik direkt (AT)",
            "price": 302.6,
            "offer_link": "https://direkt.jacob.de/produkte/asus-tuf-gaming-90lm07l0-b02370-artnr-8114075.html?utm_source=geizhals&utm_medium=cpc&utm_campaign=Preisvergleich&ref=103",
            "promotion_description": null
        },
        {
            "shop_name": "galaxus.at",
            "price": 302.98,
            "offer_link": "https://www.galaxus.at/de/s1/product/asus-vg32aqa1a-2560-x-1440-pixel-3150-monitor-23482094?utm_content=5-8&utm_campaign=preisvergleich&utm_source=geizhals&utm_medium=cpc&supplier=2705624",
            "promotion_description": null
        },
        {
            "shop_name": "neon24.de",
            "price": 309.0,
            "offer_link": "https://www.neon24.de/ASUS-TUF-Gaming-VG32AQA1A-315",
            "promotion_description": null
        },
        {
            "shop_name": "Amazon.at",
            "price": 309.09,
            "offer_link": "https://www.amazon.de/dp/B0BPC6LWK3?linkCode=xm2&camp=2025&creative=165953&smid=A3JWKAKR8XB7XF&creativeASIN=B0BPC6LWK3&tag=geizhals1-21",
            "promotion_description": null
        },
        {
            "shop_name": "computeruniverse.at",
            "price": 316.74,
            "offer_link": "https://www.computeruniverse.net/de/p/90919284?country=at&utm_channel=psm&utm_source=geizhals_at&utm_campaign=cpc&utm_medium=katalog&utm_content=artikel&agt=10395",
            "promotion_description": null
        },
        {
            "shop_name": "asus-eshop",
            "price": 319.9,
            "offer_link": "https://ebay.de/itm/364116312341?var=0&mkevt=1&mkcid=1&toolid=20006&mkrid=707-53477-19255-0&campid=5337412747",
            "promotion_description": null
        },
        {
            "shop_name": "OTTO \u00d6sterreich",
            "price": 323.99,
            "offer_link": "https://www.ottoversand.at/p/54665733-0/?IWL=116&WKZ=10&NUMSArt=10202010393820&NUMSArtPc=10202010393821&AffiliateID=geizhals&ActionID=preissuchmaschinen&utm_medium=ppsm&utm_source=geizhals&utm_campaign=preissuchmaschinen&utm_content=geizhals&Name=54665733-0",
            "promotion_description": null
        },
        {
            "shop_name": "Universal Versand",
            "price": 323.99,
            "offer_link": "https://www.universal.at/p/54665733-0?AffiliateID=geizhals&ActionID=preissuchmaschinen&Name=feed_geizhals&WKZ=61&IWL=10&NUMSArt=90102010313070&NUMSArtPc=90102010313071&utm_source=geizhals&utm_medium=ppsm&utm_campaign=preissuchmaschinen&utm_content=feed_geizhals",
            "promotion_description": null
        },
        {
            "shop_name": "e-tec.at",
            "price": 324.0,
            "offer_link": "https://www.e-tec.at/details.php?artnr=363769",
            "promotion_description": null
        },
        {
            "shop_name": "Cyberport.at",
            "price": 324.0,
            "offer_link": "https://click.cptrack.de/?rd=true&k=H2jZOPSoNfIohcnyCFLwAyhA6o4q59X7bblnbja3C5kAdKij4XuJMjSpmHQAwNB_Gy_yTbYED5SeNM2e6jUszA~~&rdlink=https%3A%2F%2Fwww.cyberport.at%2F%3FDEEP%3D6135-0H4%26APID%3D66",
            "promotion_description": null
        },
        {
            "shop_name": "Alternate.at",
            "price": 325.0,
            "offer_link": "https://www.alternate.at/ASUS/TUF-Gaming-VG32AQA1A-Gaming-Monitor/html/product/1891717?partner=AtGeizhalsat&campaign=Monitor/ASUS/1891717",
            "promotion_description": null
        },
        {
            "shop_name": "DiTech.at",
            "price": 327.9,
            "offer_link": "https://www.ditech.at/details.php?artnr=363769",
            "promotion_description": null
        },
        {
            "shop_name": "HiQ24",
            "price": 330.9,
            "offer_link": "https://www.hiq24.de/shop/artikel/336067/?sPartner=geizhals",
            "promotion_description": null
        },
        {
            "shop_name": "SNOGARD",
            "price": 330.9,
            "offer_link": "http://www.snogard.de/?kr_target=?artikelId=MON000140893&kr_tag=0104&kr_category=MON000140893",
            "promotion_description": null
        },
        {
            "shop_name": "1ashop.at",
            "price": 339.44,
            "offer_link": "https://www.1ashop.at/de/produkt/117625/asus-tuf-gaming-vg32aqa1a-led-monitor-gaming-81-3-cm-32.html",
            "promotion_description": null
        },
        {
            "shop_name": "Cyberport Stores \u00d6sterreich",
            "price": 339.9,
            "offer_link": "https://www.cyberport.at/?DEEP=6135-0H4&APID=294&STOREID=7",
            "promotion_description": null
        },
        {
            "shop_name": "BA-Computer",
            "price": 340.04,
            "offer_link": "https://www.ba-computer.at/asus-tuf-gaming-vg32aqa1a-led-monitor-gaming-81-3-cm-32-90lm07l0-b02370.html",
            "promotion_description": null
        },
        {
            "shop_name": "HEINZSOFT (AT)",
            "price": 340.84,
            "offer_link": "https://www.heinzsoft-shop.de/asus-tuf-gaming-vg32aqa1a-led-monitor.html?refID=geizhals",
            "promotion_description": null
        },
        {
            "shop_name": "TechnikLaden",
            "price": 341.93,
            "offer_link": "https://technikladen.at/P-90LM07L0-B02370-ASUS-VG32AQA1A-TUF-Gaming-315inch-WQHD-315-1-ms-90LM07L0-B02370-Displays-Projektoren?tl=gzhls",
            "promotion_description": null
        },
        {
            "shop_name": "Syswork",
            "price": 344.0,
            "offer_link": "https://syswork.at/sw/index.html?open&mid=Artikel&artid=mon-1479&from=geizhals.at",
            "promotion_description": null
        },
        {
            "shop_name": "CLS-IT",
            "price": 344.16,
            "offer_link": "https://www.cls.at/product/4518279/gh",
            "promotion_description": null
        },
        {
            "shop_name": "Future-X.at",
            "price": 344.59,
            "offer_link": "https://www.future-x.at/asus-tuf-gaming-vg32aqa1a-led-monitor-81-3-cm-32-315-sichtbar-2560-x-1440-wqhd-%40-170-hz-va-300-cd-m%B2-3000%3A1-hdr10-1-ms-2xhdmi-displayport-lautsprecher-p-9132695/?pv=2",
            "promotion_description": null
        },
        {
            "shop_name": "SKC Computer & Multimedia Store",
            "price": 355.9,
            "offer_link": "https://www.skc.at/produkte/tfts/asus_tuf_gaming_vg32aqa1a_-_led-monitor_-_gaming_-_81.3_cm_32-233232",
            "promotion_description": null
        },
        {
            "shop_name": "ElectronicShop24",
            "price": 361.0,
            "offer_link": "https://www.electronicshop24.at/product_info.php?products_id=420000001463304802&ano=U1463304802&mno=90LM07L0-B02370&ean=4711081907466&utm_medium=cpc&utm_campaign=preisvergleich&utm_content=item&utm_source=geizhals&ref=geizhals",
            "promotion_description": null
        },
        {
            "shop_name": "Syswork",
            "price": 367.0,
            "offer_link": "https://pvn.geizhals.de/trck/eclick/?campaign_alias=shoepping-at&project_alias=geizhals.de&admedia_alias=offerclick&subid=pv&url=https%3A%2F%2Fwww.shoepping.at%2Fp%2Fmonitore%2Fasus-tuf-gaming-315-vg32aqa1a-m0000LNMQ8%3Futm_source%3Dpsm%26utm_medium%3Dgeizhals%26utm_campaign%3Dm0000LNMQ8",
            "promotion_description": null
        },
        {
            "shop_name": "ms-it-beratung",
            "price": 369.0,
            "offer_link": "https://ms-it-beratung.at/shop/details.php?art=420297&artname=ASUS+TUF+Gaming+VG32AQA1A+80.1cm+%2816%3A9%29+WQHD+HDMI+DP",
            "promotion_description": null
        },
        {
            "shop_name": "Waldbauer",
            "price": 369.0,
            "offer_link": "http://www.waldbauer.com/detail.php?art=i343230323937&ads=gh",
            "promotion_description": null
        },
        {
            "shop_name": "TaufNaus",
            "price": 369.72,
            "offer_link": "https://www.taufnaus.de/product/10611287",
            "promotion_description": null
        },
        {
            "shop_name": "bauguru",
            "price": 371.5,
            "offer_link": "https://restposten.bauguru.at/monitore/126670-monitor-asus-90lm07l0-b02370-31-5-4711081907466.html",
            "promotion_description": null
        },
        {
            "shop_name": "I-CS",
            "price": 375.9,
            "offer_link": "https://www.i-cs.at/eshop.php?action=article_detail&s_supplier_aid=25966862&rid=Geizhals",
            "promotion_description": null
        },
        {
            "shop_name": "edigital.at",
            "price": 390.0,
            "offer_link": "https://click.edigital.at/monitor/asus-315-tuf-gaming-vg32aqa1a-monitor-va-led-p1039361?utm_source=geizhals.at&utm_medium=price-comparison&utm_term=1039361",
            "promotion_description": null
        },
        {
            "shop_name": "Conrad.at",
            "price": 399.0,
            "offer_link": "https://www.conrad.at/de/p/2793368?insert=7M&utm_source=geizhals&utm_medium=cpc&utm_campaign=pvgl&utm_content=dl_article",
            "promotion_description": null
        },
        {
            "shop_name": "TaufNaus",
            "price": 418.29,
            "offer_link": "https://www.taufnaus.de/product/10608542",
            "promotion_description": null
        }
    ]
}