{
    "url": "https://geizhals.at/msi-optix-g271cde-9s6-3cc32h-013-a2741987.html?hloc=at&hloc=de",
    "product_name": "MSI Optix G271CDE, 27\"",
    "product_details": [
        {
            "name": "Diagonale",
            "value": "27\"/\u200b68.6cm"
        },
        {
            "name": "Aufl\u00f6sung",
            "value": "1920x1080, 16:9, 82ppi"
        },
        {
            "name": "Helligkeit",
            "value": "300cd/\u200bm\u00b2"
        },
        {
            "name": "Kontrast",
            "value": "3.000:1 (statisch), 100.000.000:1 (dynamisch)"
        },
        {
            "name": "Reaktionszeit",
            "value": "4ms (GtG), 1ms (MPRT)"
        },
        {
            "name": "Blickwinkel",
            "value": "178\u00b0/\u200b178\u00b0"
        },
        {
            "name": "Panel",
            "value": "VA"
        },
        {
            "name": "Form",
            "value": "gebogen (curved), 1000R/\u200b1m"
        },
        {
            "name": "Beschichtung",
            "value": "matt (non-glare)"
        },
        {
            "name": "Hintergrundbeleuchtung",
            "value": "White-LED, flicker-free, Blaulichtfilter"
        },
        {
            "name": "HDR",
            "value": "N/\u200bA"
        },
        {
            "name": "Farbtiefe",
            "value": "8bit (16.7 Mio. Farben)"
        },
        {
            "name": "FRC",
            "value": "unbekannt"
        },
        {
            "name": "Farbraum",
            "value": "115% (sRGB), 95% (Adobe RGB), 90% (DCI-P3), 115% (REC 709), keine Angabe (REC 2020)"
        },
        {
            "name": "Bildwiederholfrequenz",
            "value": "165Hz"
        },
        {
            "name": "Variable Synchronisierung",
            "value": "Adaptive Sync, AMD FreeSync Premium (48-165Hz via HDMI, 48-165Hz via DisplayPort, mit LFC-Support, ohne HDR)"
        },
        {
            "name": "Signalfrequenz",
            "value": "104-186.8kHz (horizontal), 48-165Hz (vertikal)"
        },
        {
            "name": "Anschl\u00fcsse",
            "value": "2x HDMI 2.0 (165Hz@1920x1080), 1x DisplayPort 1.2a (165Hz@1920x1080)"
        },
        {
            "name": "Weitere Anschl\u00fcsse",
            "value": "N/\u200bA"
        },
        {
            "name": "USB-Hub Out",
            "value": "N/\u200bA"
        },
        {
            "name": "USB-Hub In",
            "value": "N/\u200bA"
        },
        {
            "name": "Audio",
            "value": "1x Line-Out"
        },
        {
            "name": "Ergonomie",
            "value": "N/\u200bA (h\u00f6henverstellbar), N/\u200bA (Pivot), N/\u200bA (drehbar), +20\u00b0/\u200b-5\u00b0 (neigbar), keine Angabe (Schr\u00e4glage)"
        },
        {
            "name": "Farbe",
            "value": "schwarz (Displayrahmen), schwarz (untere Blende), schwarz (Standfu\u00df), schwarz/\u200brot (R\u00fcckseite)"
        },
        {
            "name": "VESA",
            "value": "75x75 (belegt)"
        },
        {
            "name": "Leistungsaufnahme",
            "value": "keine Angabe (maximal), 25W (typisch), keine Angabe (Energielabel alt A+++ bis G), 0.5W (Standby)"
        },
        {
            "name": "Energieeffizienzklasse SDR (A bis G)",
            "value": "F"
        },
        {
            "name": "Energieverbrauch SDR",
            "value": "26kWh/\u200b1000h"
        },
        {
            "name": "Stromversorgung",
            "value": "AC-In (internes Netzteil)"
        },
        {
            "name": "Anwendung",
            "value": "station\u00e4r"
        },
        {
            "name": "Screen-to-Body-Ratio",
            "value": "91.3% (berechnet)"
        },
        {
            "name": "Abmessungen (BxHxT)",
            "value": "606.5x482.2x245.6mm (mit Standfu\u00df), 606.5x363x115.1mm (ohne Standfu\u00df)"
        },
        {
            "name": "Gewicht",
            "value": "5.60kg (mit Standfu\u00df), 4.10kg (ohne Standfu\u00df)"
        },
        {
            "name": "Besonderheiten",
            "value": "Slim Bezel, mechanische Tasten, Steuerkreuz, Sicherheitsschloss (Kensington), HDCP 2.2"
        },
        {
            "name": "Herstellergarantie",
            "value": "drei Jahre (Pickup&Return)"
        },
        {
            "name": "USB-Schreibweise",
            "value": "Link"
        },
        {
            "name": "Letztes Preisupdate",
            "value": "02.10.2023, 13:57"
        },
        {
            "name": "Gelistet seit",
            "value": "25.05.2022, 15:50"
        }
    ],
    "offers": [
        {
            "shop_name": "DiTech.at",
            "price": 224.9,
            "offer_link": "https://www.ditech.at/details.php?artnr=358613",
            "promotion_description": null
        },
        {
            "shop_name": "e-tec.at",
            "price": 224.9,
            "offer_link": "https://www.e-tec.at/details.php?artnr=358613",
            "promotion_description": null
        },
        {
            "shop_name": "galaxus.at",
            "price": 240.64,
            "offer_link": "https://www.galaxus.at/de/s1/product/msi-optix-g271cde-1920-x-1080-pixel-27-monitor-21147403?utm_content=2w&utm_campaign=preisvergleich&utm_source=geizhals&utm_medium=cpc&supplier=2705624",
            "promotion_description": null
        },
        {
            "shop_name": "Cyberport Stores \u00d6sterreich",
            "price": 319.0,
            "offer_link": "https://www.cyberport.at/?DEEP=6117-022&APID=294&STOREID=7",
            "promotion_description": null
        },
        {
            "shop_name": "Cyberport.at",
            "price": 319.0,
            "offer_link": "https://click.cptrack.de/?rd=true&k=H2jZOPSoNfIohcnyCFLwAxiNp2m7lhfDBmxbkivOr9Q21EF7_htO_byj2ZcF3rh9Gy_yTbYED5SeNM2e6jUszA~~&rdlink=https%3A%2F%2Fwww.cyberport.at%2F%3FDEEP%3D6117-022%26APID%3D66",
            "promotion_description": null
        },
        {
            "shop_name": "playox (AT)",
            "price": 321.67,
            "offer_link": "https://www.playox.de/productredirect/index/sku/23960013?sPartner=p-geizhals-at&campaign=psm/geizhals-at/",
            "promotion_description": null
        },
        {
            "shop_name": "office-partner (AT)",
            "price": 321.68,
            "offer_link": "https://www.office-partner.de/productredirect/index/sku/23960013?sPartner=p-geizhals-at&campaign=psm/geizhals-at/",
            "promotion_description": null
        },
        {
            "shop_name": "mylemon.at",
            "price": 322.31,
            "offer_link": "https://www.mylemon.at/artikel/msi/9s6_3cc32h_013/optix-g271cde.html",
            "promotion_description": null
        },
        {
            "shop_name": "haym.infotec",
            "price": 322.32,
            "offer_link": "https://haym.info/produktdetails?id=2C15397",
            "promotion_description": null
        },
        {
            "shop_name": "CSV-Direct.de",
            "price": 322.95,
            "offer_link": "https://www.csv-direct.de/artinfo.php?artnr=AGX1596893&KATEGORIE=162&pva=geizhals2",
            "promotion_description": null
        },
        {
            "shop_name": "Alternate.at",
            "price": 324.0,
            "offer_link": "https://www.alternate.at/MSI/Optix-G271CDE-Gaming-Monitor/html/product/1854558?partner=AtGeizhalsat&campaign=Monitor/MSI/1854558",
            "promotion_description": null
        },
        {
            "shop_name": "Proshop.at",
            "price": 342.8,
            "offer_link": "https://www.proshop.at/Bildschirm/MSI-27-Bildschirm-Optix-G271CDE-Black-1-ms-AMD-FreeSync-Premium/3188834?utm_source=geizhals&utm_medium=cpc&utm_campaign=pricesite",
            "promotion_description": null
        },
        {
            "shop_name": "Jacob Elektronik direkt (AT)",
            "price": 351.91,
            "offer_link": "https://direkt.jacob.de/produkte/msi-optix-g271cde-9s6-3cc32h-013-artnr-7907159.html?utm_source=geizhals&utm_medium=cpc&utm_campaign=Preisvergleich&ref=103",
            "promotion_description": null
        },
        {
            "shop_name": "TaufNaus",
            "price": 380.24,
            "offer_link": "https://www.taufnaus.de/product/10607565",
            "promotion_description": null
        }
    ]
}