{
    "html_file": "offer_1106_41.html",
    "name": "BenQ PD3205U, 31.5\"",
    "offer_link": "https://restposten.bauguru.at/monitore/128342-monitor-benq-9h-lkgla-tbe-31-5-4k-ultra-hd-led-ips-4718755086601.html",
    "price": 906.8,
    "raw_specifications": {
        "Art": "Achse",
        "Aufl\u00f6sung": "4K Ultra HD",
        "Aufl\u00f6sung (px)": "3840 x 2160 px",
        "Betriebssystem": "Windows 10 Pro",
        "Diagonale des Bildschirms (cm)": "80 cm",
        "Enthalten": "Kopfh\u00f6rerausgang",
        "Frequenz": "60 Hz",
        "Geschwindigkeit": "60 Hz",
        "Glanz": "350 lm ANSI",
        "Kompatibel": "VESA 100 x 100 mm",
        "Kontrastverh\u00e4ltnis": "1000:1",
        "Maximale Anpassung": "110 mm",
        "Montage": "VESA",
        "Ports": "2",
        "Seitenverh\u00e4ltnis": "16:9",
        "Spannung": "100-240 V",
        "Steckbares Produkt": "Ja",
        "Steckertyp": "EU-Stecker",
        "Verbindung": "DisplayPort 1.4",
        "Winkel": "178\u00ba"
    },
    "raw_specifications_text": "Seitenverh\u00e4ltnis: 16:9\nAufl\u00f6sung: 4K Ultra HD\nSpannung: 100-240 V\nFrequenz: 60 Hz\nKompatibel: VESA 100 x 100 mm\nAufl\u00f6sung (px): 3840 x 2160 px\nSteckbares Produkt: Ja\nSteckertyp: EU-Stecker\nDiagonale des Bildschirms (cm): 80 cm\nArt: Achse\nKontrastverh\u00e4ltnis: 1000:1\nPorts: 2\nBetriebssystem: Windows 10 Pro\nGlanz: 350 lm ANSI\nEnthalten: Kopfh\u00f6rerausgang\nWinkel: 178\u00ba\nVerbindung: DisplayPort 1.4\nMontage: VESA\nGeschwindigkeit: 60 Hz\nMaximale Anpassung: 110 mm",
    "reference_file": "offer_reference_1106.json",
    "shop_name": "bauguru"
}