{
    "html_file": "offer_970_13.html",
    "name": "Lenovo G27qe-20, 27\"",
    "offer_link": "https://technikladen.at/I-66E1GAR1EU-Lenovo-G27qe-20-66E1GAR1EU-Displays-Projektoren?tl=gzhls",
    "price": 325.13,
    "raw_specifications": {
        "Bildschirmaufl\u00f6sung": "2560 x 1440 Pixel",
        "Bildschirmdiagonale": "68,6 cm",
        "Bildschirmtechnologie": "LED",
        "Blickwinkel, horizontal": "178 \u00b0",
        "Blickwinkel, vertikal": "178 \u00b0",
        "HD-Typ": "Quad HD",
        "H\u00f6henverstellung": "Ja",
        "Natives Seitenverh\u00e4ltnis": "16:9",
        "Produktfarbe": "Schwarz",
        "Reaktionszeit": "7 ms",
        "VESA-Halterung": "Ja"
    },
    "raw_specifications_text": "Bildschirmdiagonale: 68,6 cm\nBildschirmaufl\u00f6sung: 2560 x 1440 Pixel\nHD-Typ: Quad HD\nBildschirmtechnologie: LED\nReaktionszeit: 7 ms\nNatives Seitenverh\u00e4ltnis: 16:9\nBlickwinkel, horizontal: 178 \u00b0\nBlickwinkel, vertikal: 178 \u00b0\nVESA-Halterung: Ja\nH\u00f6henverstellung: Ja\nProduktfarbe: Schwarz",
    "reference_file": "offer_reference_970.json",
    "shop_name": "TechnikLaden"
}