{
    "html_file": "offer_659_12.html",
    "name": "Lenovo ThinkVision P24h-30, 23.8\"",
    "offer_link": "https://www.proshop.at/Bildschirm/Lenovo-24-Bildschirm-ThinkVision-P24h-30-Black-4-ms/3159625?utm_source=geizhals&utm_medium=cpc&utm_campaign=pricesite",
    "price": 338.39,
    "raw_specifications": {
        "Abmessungen (Breite x Tiefe x H\u00f6he)": "53.95 cm x 19.97 cm x 34.88 cm - mit Fu\u00df",
        "Abmessungen (Breite x Tiefe x H\u00f6he) - mit Fu\u00df": "53.95 cm x 19.97 cm x 34.88 cm",
        "Besonderheiten": "Augenkomfort-Modus, HDR10-kompatibel, NearEdgeless-Design an 3 Seiten, 8-bit (6-bit + FRC) Farbtiefe, Natural Low Blue Light Technology, Modularer Kamera-Support, modularer Soundbar-Support",
        "Bildschirmbeschichtung": "Blendfrei",
        "Bildschirmtyp": "IPS",
        "Details zu Abmessungen & Gewicht": "Mit Standfu\u00df (niedrigste Position) - Breite: 53.95 cm - Tiefe: 19.97 cm - H\u00f6he: 34.88 cm - Gewicht: 5.7 kg  Mit Standfu\u00df (h\u00f6chste Position) - Breite: 53.95 cm - Tiefe: 19.97 cm - H\u00f6he: 50.38 cm - Gewicht: 5.7 kg  Ohne Fu\u00df - Breite: 53.95 cm - Tiefe: 4.65 cm - H\u00f6he: 32.37 cm - Gewicht: 3.8 kg",
        "Diagonalabmessung": "60.5 cm (23.8\")",
        "Display-Typ": "LED-hintergrundbeleuchteter LCD-Monitor / TFT-Aktivmatrix",
        "EAN": "0196380976834",
        "ENERGY STAR zertifiziert": "Ja",
        "EPEAT-kompatibel": "EPEAT Gold",
        "Eingangsanschl\u00fcsse": "HDMI, DisplayPort, USB-C",
        "Eingangsspannung": "Wechselstrom 100-240 V (50/60 Hz)",
        "Einstellungen der Anzeigeposition": "H\u00f6he, Pivot (Rotation), Drehung, Neigung",
        "Energierverbrauch Sleep": "0.5 Watt",
        "Enthaltene Kabel": "1 x USB-C auf USB-A Kabel - 1.8 m  1 x Stromkabel - 1.8 m  1 x HDMI-Kabel - 1.8 m  1 x USB-C 3.1 Gen 1 Kabel - 1.8 m",
        "Entwickelt f\u00fcr": "ThinkPad P15 Gen 2 20YQ",
        "Erforderliches Betriebssystem": "Windows 10, Windows 11",
        "Ethernet integriert": "Ja",
        "Farbe": "Raven Black",
        "Farbraum": "99% BT.709, 99% sRGB",
        "Farbunterst\u00fctzung": "16,7 Millionen Farben",
        "Ger\u00e4tetyp": "LED-hintergrundbeleuchteter LCD-Monitor - 60.5 cm (23.8\")",
        "Gewicht": "5.7 kg",
        "Helligkeit": "300 cd/m\u00b2",
        "Hersteller": "Lenovo",
        "Hintergrundbeleuchtungs-Technologie": "WLED",
        "Horizontaler Betrachtungswinkel": "178",
        "H\u00f6heneinstellung": "155 mm",
        "Integrierte Peripherieger\u00e4te": "Gigabit Ethernet-Netzwerkadapter, USB 3.2 Gen 1 Hub",
        "Kennzeichnung": "CCC, RoHS 2011/65/EU, TUV Rheinland Low Blue Light Certification, TUV Rheinland Flicker Free Certification, TUV Rheinland Eye Comfort Certification, China Energy standard Tier 1, TUV Eyesafe Display Certification, TUV Rheinland Low Blue Light (Hardware Solution)",
        "Kontrast": "1000:1 / 3000000:1 (dynamisch)",
        "Leistungsmerkmale": "Slot f\u00fcr Sicherheitsschloss (Kabelschloss getrennt erh\u00e4ltlich), integrierte Kabelf\u00fchrung, abnehmbarer St\u00e4nder",
        "Lokalisierung": "Englisch / Europa",
        "Modell": "63B3GAT6EU",
        "Native Aufl\u00f6sung": "QHD 2560 x 1440 bei 60 Hz",
        "Neigungswinkel": "-5/23.5",
        "Pixelpitch": "0.205 mm",
        "Ppi": "123",
        "Produktbeschreibung": "Lenovo ThinkVision P24h-30 - LED-Monitor - QHD - 60.5 cm (23.8\")",
        "Reaktionszeit": "4 ms (extrem), 6 ms (typisch)",
        "Rotationswinkel": "180",
        "Schlosstyp zur Diebstahlsicherung": "Kensington Slot",
        "Schnittstellen": "HDMI  DisplayPort 1.4  DisplayPort-Ausgang  USB-C 3,2 Gen 1 Upstream (Type C)  USB-C 3.2 Gen 1 Downstream (BC 1.2)  Audio Line-Out  Netzwerk (RJ-45)",
        "Schwenkwinkel": "90",
        "Seitenverh\u00e4ltnis": "16:9",
        "Spannung": "Wechselstrom 100-240 V (50/60 Hz)",
        "Stromverbrauch (Aus-Modus)": "0.3 Watt",
        "Stromverbrauch (max.)": "161 Watt",
        "Stromverbrauch (typisch)": "27 Watt",
        "TCO-zertifiziert": "TCO Certified Edge Displays, TCO Certified Displays 9",
        "Transportbreite": "62 cm",
        "Transportgewicht": "8.6 kg",
        "Transporth\u00f6he": "42 cm",
        "Transporttiefe": "16 cm",
        "Umweltschutzstandards": "TCO Certified Edge Displays, TCO Certified Displays 9, ENERGY STAR-qualifiziert EPEAT Gold",
        "VESA-Halterung": "100 x 100 mm",
        "Vertikaler Betrachtungswinkel": "178",
        "Waren-Nr.": "3159625",
        "Zum Hersteller": "lenovo.com"
    },
    "raw_specifications_text": "Hersteller: Lenovo\nWaren-Nr.: 3159625\nModell: 63B3GAT6EU\nEAN: 0196380976834\nZum Hersteller: lenovo.com\nProduktbeschreibung: Lenovo ThinkVision P24h-30 - LED-Monitor - QHD - 60.5 cm (23.8\")\nGer\u00e4tetyp: LED-hintergrundbeleuchteter LCD-Monitor - 60.5 cm (23.8\")\nLeistungsmerkmale: Slot f\u00fcr Sicherheitsschloss (Kabelschloss getrennt erh\u00e4ltlich), integrierte Kabelf\u00fchrung, abnehmbarer St\u00e4nder\nBildschirmtyp: IPS\nSeitenverh\u00e4ltnis: 16:9\nNative Aufl\u00f6sung: QHD 2560 x 1440 bei 60 Hz\nPixelpitch: 0.205 mm\nHelligkeit: 300 cd/m\u00b2\nKontrast: 1000:1 / 3000000:1 (dynamisch)\nReaktionszeit: 4 ms (extrem), 6 ms (typisch)\nFarbunterst\u00fctzung: 16,7 Millionen Farben\nFarbraum: 99% BT.709, 99% sRGB\nEingangsanschl\u00fcsse: HDMI, DisplayPort, USB-C\nEthernet integriert: Ja\nEinstellungen der Anzeigeposition: H\u00f6he, Pivot (Rotation), Drehung, Neigung\nBildschirmbeschichtung: Blendfrei\nSpannung: Wechselstrom 100-240 V (50/60 Hz)\nFarbe: Raven Black\nAbmessungen (Breite x Tiefe x H\u00f6he) - mit Fu\u00df: 53.95 cm x 19.97 cm x 34.88 cm\nGewicht: 5.7 kg\nLokalisierung: Englisch / Europa\nUmweltschutzstandards: TCO Certified Edge Displays, TCO Certified Displays 9, ENERGY STAR-qualifiziert EPEAT Gold\nKennzeichnung: CCC, RoHS 2011/65/EU, TUV Rheinland Low Blue Light Certification, TUV Rheinland Flicker Free Certification, TUV Rheinland Eye Comfort Certification, China Energy standard Tier 1, TUV Eyesafe Display Certification, TUV Rheinland Low Blue Light (Hardware Solution)\nEntwickelt f\u00fcr: ThinkPad P15 Gen 2 20YQ\nDisplay-Typ: LED-hintergrundbeleuchteter LCD-Monitor / TFT-Aktivmatrix\nDiagonalabmessung: 60.5 cm (23.8\")\nIntegrierte Peripherieger\u00e4te: Gigabit Ethernet-Netzwerkadapter, USB 3.2 Gen 1 Hub\nPpi: 123\nHorizontaler Betrachtungswinkel: 178\nVertikaler Betrachtungswinkel: 178\nHintergrundbeleuchtungs-Technologie: WLED\nBesonderheiten: Augenkomfort-Modus, HDR10-kompatibel, NearEdgeless-Design an 3 Seiten, 8-bit (6-bit + FRC) Farbtiefe, Natural Low Blue Light Technology, Modularer Kamera-Support, modularer Soundbar-Support\nAbmessungen (Breite x Tiefe x H\u00f6he): 53.95 cm x 19.97 cm x 34.88 cm - mit Fu\u00df\nSchnittstellen: HDMI  DisplayPort 1.4  DisplayPort-Ausgang  USB-C 3,2 Gen 1 Upstream (Type C)  USB-C 3.2 Gen 1 Downstream (BC 1.2)  Audio Line-Out  Netzwerk (RJ-45)\nNeigungswinkel: -5/23.5\nSchwenkwinkel: 90\nRotationswinkel: 180\nH\u00f6heneinstellung: 155 mm\nVESA-Halterung: 100 x 100 mm\nEnthaltene Kabel: 1 x USB-C auf USB-A Kabel - 1.8 m  1 x Stromkabel - 1.8 m  1 x HDMI-Kabel - 1.8 m  1 x USB-C 3.1 Gen 1 Kabel - 1.8 m\nSchlosstyp zur Diebstahlsicherung: Kensington Slot\nEingangsspannung: Wechselstrom 100-240 V (50/60 Hz)\nStromverbrauch (typisch): 27 Watt\nStromverbrauch (max.): 161 Watt\nEnergierverbrauch Sleep: 0.5 Watt\nStromverbrauch (Aus-Modus): 0.3 Watt\nErforderliches Betriebssystem: Windows 10, Windows 11\nDetails zu Abmessungen & Gewicht: Mit Standfu\u00df (niedrigste Position) - Breite: 53.95 cm - Tiefe: 19.97 cm - H\u00f6he: 34.88 cm - Gewicht: 5.7 kg  Mit Standfu\u00df (h\u00f6chste Position) - Breite: 53.95 cm - Tiefe: 19.97 cm - H\u00f6he: 50.38 cm - Gewicht: 5.7 kg  Ohne Fu\u00df - Breite: 53.95 cm - Tiefe: 4.65 cm - H\u00f6he: 32.37 cm - Gewicht: 3.8 kg\nTransportbreite: 62 cm\nTransporttiefe: 16 cm\nTransporth\u00f6he: 42 cm\nTransportgewicht: 8.6 kg\nTCO-zertifiziert: TCO Certified Edge Displays, TCO Certified Displays 9\nEPEAT-kompatibel: EPEAT Gold\nENERGY STAR zertifiziert: Ja",
    "reference_file": "offer_reference_659.json",
    "shop_name": "Proshop.at"
}