{
    "html_file": "offer_686_34.html",
    "name": "Philips S-line 275S9JAL, 27\"",
    "offer_link": "https://www.galaxus.at/de/s1/product/philips-lcd-monitor-27-monitor-23328347?utm_content=1-2w&utm_campaign=preisvergleich&utm_source=geizhals&utm_medium=cpc&supplier=2705624",
    "price": 209.54,
    "raw_specifications": {
        "Artikelnummer": "23328347"
    },
    "raw_specifications_text": "Artikelnummer: 23328347",
    "reference_file": "offer_reference_686.json",
    "shop_name": "galaxus.at"
}