{
    "html_file": "offer_2317_22.html",
    "name": "BenQ PhotoVue SW240, 24.1\"",
    "offer_link": "https://haym.info/produktdetails?id=8C17573",
    "price": 523.4,
    "raw_specifications": {
        "Artikelnummer": "8C17573",
        "Aufl\u00f6sung": "1920x1200 (16:10)",
        "Bildschirmdiagonale/Zoll": "24.1 Zoll",
        "Bildschirmdiagonale/cm": "61.2 cm",
        "DVI": "1x",
        "DisplayPort": "1x",
        "Energieeffizienzklasse": "E",
        "HDMI": "1x",
        "Helligkeit": "250 cd/m2",
        "Herstellergarantie": "36 Monate",
        "H\u00f6henverstellbarkeit": "ja",
        "Lautsprecher": "nein",
        "Paneltyp": "IPS",
        "Pivotfunktion": "ja",
        "Reaktionszeit": "5 Millisekunden",
        "Swivelfunktion": "ja",
        "Touch-Funktion": "nein",
        "VESA-Bohrung": "100x100",
        "VGA": "0x"
    },
    "raw_specifications_text": "Bildschirmdiagonale/Zoll: 24.1 Zoll\nAufl\u00f6sung: 1920x1200 (16:10)\nPaneltyp: IPS\nH\u00f6henverstellbarkeit: ja\nEnergieeffizienzklasse: E\nVGA: 0x\nDVI: 1x\nDisplayPort: 1x\nHDMI: 1x\nVESA-Bohrung: 100x100\nSwivelfunktion: ja\nPivotfunktion: ja\nLautsprecher: nein\nReaktionszeit: 5 Millisekunden\nHelligkeit: 250 cd/m2\nBildschirmdiagonale/cm: 61.2 cm\nTouch-Funktion: nein\nArtikelnummer: 8C17573\nHerstellergarantie: 36 Monate",
    "reference_file": "offer_reference_2317.json",
    "shop_name": "haym.infotec"
}