{
    "html_file": "offer_356_1.html",
    "name": "LG 32UN550P-W, 31.5\"",
    "offer_link": "https://www.amazon.de/dp/B0BXBC3VTH?linkCode=xm2&camp=2025&creative=165953&smid=A3JWKAKR8XB7XF&creativeASIN=B0BXBC3VTH&tag=geizhals1-21",
    "price": 301.5,
    "raw_specifications": {
        "ASIN": "B0BXBC3VTH",
        "Amazon Bestseller-Rang": "Nr. 10,262 in Computer & Zubeh\u00f6r (Siehe Top 100 in Computer & Zubeh\u00f6r)  Nr. 209 in Monitore",
        "Anzahl HDMI Schnittstellen": "\u200e2",
        "Artikelgewicht": "\u200e11,2 Kilograms",
        "Batterien enthalten": "\u200eNein",
        "Bildschirmaufl\u00f6sung": "\u200e3.84 x 2.16",
        "Display-Gr\u00f6\u00dfe": "\u200e32 Zoll",
        "Durchschnittliche Kundenbewertung": "4,4  4,4 von 5 Sternen    \n    66 Sternebewertungen   \n\n\n 4,4 von 5 Sternen",
        "Farbe": "\u200eSchwarz",
        "Garantierte Software-Updates bis": "\u200eunbekannt",
        "Hersteller": "\u200eLG Electronics",
        "Im Angebot von Amazon.de seit": "2. M\u00e4rz 2023",
        "L\u00f6sung": "\u200e3840 x 2160 Pixels",
        "Marke": "\u200eLG Electronics",
        "Modell/Serie": "\u200e32UN550P-W.AEU",
        "Modellnummer": "\u200e32UN550P-W.AEU",
        "Produktabmessungen": "\u200e82 x 51 x 23 cm; 11,2 Kilogramm"
    },
    "raw_specifications_text": "Marke: \u200eLG Electronics\nHersteller: \u200eLG Electronics\nModell/Serie: \u200e32UN550P-W.AEU\nProduktabmessungen: \u200e82 x 51 x 23 cm; 11,2 Kilogramm\nModellnummer: \u200e32UN550P-W.AEU\nFarbe: \u200eSchwarz\nDisplay-Gr\u00f6\u00dfe: \u200e32 Zoll\nBildschirmaufl\u00f6sung: \u200e3.84 x 2.16\nL\u00f6sung: \u200e3840 x 2160 Pixels\nAnzahl HDMI Schnittstellen: \u200e2\nBatterien enthalten: \u200eNein\nArtikelgewicht: \u200e11,2 Kilograms\nGarantierte Software-Updates bis: \u200eunbekannt\nASIN: B0BXBC3VTH\nDurchschnittliche Kundenbewertung: 4,4  4,4 von 5 Sternen    \n    66 Sternebewertungen   \n\n\n 4,4 von 5 Sternen\nAmazon Bestseller-Rang: Nr. 10,262 in Computer & Zubeh\u00f6r (Siehe Top 100 in Computer & Zubeh\u00f6r)  Nr. 209 in Monitore\nIm Angebot von Amazon.de seit: 2. M\u00e4rz 2023",
    "reference_file": "offer_reference_356.json",
    "shop_name": "Amazon.at"
}