{
    "html_file": "offer_2259_25.html",
    "name": "Lenovo ThinkVision T23d-10, 22.5\"",
    "offer_link": "https://www.galaxus.at/de/s1/product/kapsolo-4-wege-blickschutzfolie-selbstklebend-customized-lenovo-thinkvision-t23d-2250-bildschirmfoli-32340681?utm_content=2w&utm_campaign=preisvergleich&utm_source=geizhals&utm_medium=cpc&supplier=2705624",
    "price": 191.8,
    "raw_specifications": {
        "Artikelnummer": "32340681",
        "Folienfunktion": "BlaulichtfilteriMehr Informationen zu: Blaulichtfilter",
        "Foliengr\u00f6sse": "22.50\"",
        "Sichtschutzrichtung": "HorizontaliMehr Informationen zu: Horizontal, VertikaliMehr Informationen zu: Vertikal"
    },
    "raw_specifications_text": "Foliengr\u00f6sse: 22.50\"\nFolienfunktion: BlaulichtfilteriMehr Informationen zu: Blaulichtfilter\nSichtschutzrichtung: HorizontaliMehr Informationen zu: Horizontal, VertikaliMehr Informationen zu: Vertikal\nArtikelnummer: 32340681",
    "reference_file": "offer_reference_2259.json",
    "shop_name": "galaxus.at"
}