{
    "html_file": "offer_1442_8.html",
    "name": "Lenovo ThinkVision T27h-2L, 27\"",
    "offer_link": "https://www.mylemon.at/artikel/lenovo/62b1gat2eu_5319674132_abverkauf/t27h-2l-c19270qt1-27-inch.html",
    "price": 304.3,
    "raw_specifications": {
        "Artikelnummer": "M1MYBZ5L",
        "Aufl\u00f6sung": "2560x1440",
        "Besonderheiten": "60 Hz",
        "Displaygr\u00f6\u00dfe": "27 Zoll",
        "EAN": "8592978404147",
        "Ergonomie": "H\u00f6henverstellbar, Pivot (90 Grad drehbar), Schwenkbar, Neigbar",
        "Helligkeit": "350 cd/m\u00b2",
        "Hersteller Artikelnummer": "62B1GAT2EU_5319674132_ABVERKAUF",
        "Panel": "IPS",
        "Reaktionszeit": "4 ms",
        "VESA Halterung": "100x100 mm",
        "Video Anschl\u00fcsse": "1x HDMI, 1x DisplayPort, USB-C DisplayPort"
    },
    "raw_specifications_text": "Displaygr\u00f6\u00dfe: 27 Zoll\nAufl\u00f6sung: 2560x1440\nPanel: IPS\nReaktionszeit: 4 ms\nVideo Anschl\u00fcsse: 1x HDMI, 1x DisplayPort, USB-C DisplayPort\nErgonomie: H\u00f6henverstellbar, Pivot (90 Grad drehbar), Schwenkbar, Neigbar\nVESA Halterung: 100x100 mm\nHelligkeit: 350 cd/m\u00b2\nBesonderheiten: 60 Hz\nHersteller Artikelnummer: 62B1GAT2EU_5319674132_ABVERKAUF\nEAN: 8592978404147\nArtikelnummer: M1MYBZ5L",
    "reference_file": "offer_reference_1442.json",
    "shop_name": "mylemon.at"
}