{
    "html_file": "offer_1635_4.html",
    "name": "Acer Predator X34GSbmiipphuzx, 34\"",
    "offer_link": "https://click.cptrack.de/?rd=true&k=H2jZOPSoNfIohcnyCFLwA9aNvHU84MlKs-CV6MlIxxy_wbscU0qZYOFa7Mt7xIaoGy_yTbYED5SeNM2e6jUszA~~&rdlink=https%3A%2F%2Fwww.cyberport.at%2F%3FDEEP%3D6121-4K7%26APID%3D66",
    "price": 999.0,
    "raw_specifications": {
        "Aufl\u00f6sung": "3.440x1.440 Ultra Wide QHD",
        "Betrachtungswinkel h/v": "178\u00b0/178\u00b0",
        "Bildformat": "21:9",
        "Breite in mm": "818mm",
        "DVI": "kein",
        "Displaygr\u00f6\u00dfe in Zoll": "34 Zoll",
        "Displaygr\u00f6\u00dfe in cm": "86,4 cm",
        "Displayport": "1x DP",
        "Farbraumabdeckung": "98% DCI-P3",
        "Farbtiefe": "10 Bit / 1,07 Mrd Farben",
        "Gewicht in kg": "13,3 kg",
        "HDMI": "2x HDMI",
        "Helligkeit": "400 cd/m\u00b2",
        "H\u00f6he in mm": "600mm",
        "H\u00f6henverstellbar": "130mm",
        "Jahresverbrauch": "27 kWh",
        "Kontrast dynamisch": "100.000.000:1",
        "Kontrast typisch": "1.000:1",
        "Lautsprecher": "2x",
        "Leistung": "7W",
        "Oberfl\u00e4che": "entspiegelt",
        "Reaktionszeit": "0,5 ms",
        "Technologie": "IPS",
        "Tiefe in mm": "309mm",
        "USB-C": "1x",
        "Wandmontage": "VESA100x100"
    },
    "raw_specifications_text": "Jahresverbrauch: 27 kWh\nDisplaygr\u00f6\u00dfe in cm: 86,4 cm\nDisplaygr\u00f6\u00dfe in Zoll: 34 Zoll\nTechnologie: IPS\nAufl\u00f6sung: 3.440x1.440 Ultra Wide QHD\nBildformat: 21:9\nOberfl\u00e4che: entspiegelt\nFarbraumabdeckung: 98% DCI-P3\nFarbtiefe: 10 Bit / 1,07 Mrd Farben\nHelligkeit: 400 cd/m\u00b2\nKontrast typisch: 1.000:1\nKontrast dynamisch: 100.000.000:1\nReaktionszeit: 0,5 ms\nBetrachtungswinkel h/v: 178\u00b0/178\u00b0\nHDMI: 2x HDMI\nDVI: kein\nDisplayport: 1x DP\nUSB-C: 1x\nLautsprecher: 2x\nLeistung: 7W\nH\u00f6henverstellbar: 130mm\nWandmontage: VESA100x100\nBreite in mm: 818mm\nH\u00f6he in mm: 600mm\nTiefe in mm: 309mm\nGewicht in kg: 13,3 kg",
    "reference_file": "offer_reference_1635.json",
    "shop_name": "Cyberport.at"
}